bleachfields/__init__.py
bleachfields/bleachfield.py
bleachfields/bleachjson.py
bleachfields/bleachtext.py
bleachfields/cache.py
bleachfields-1.0.2.dist-info/DESCRIPTION.rst
bleachfields-1.0.2.dist-info/METADATA
bleachfields-1.0.2.dist-info/metadata.json
bleachfields-1.0.2.dist-info/pbr.json
bleachfields-1.0.2.dist-info/RECORD
bleachfields-1.0.2.dist-info/top_level.txt
bleachfields-1.0.2.dist-info/WHEEL
