Metadata-Version: 2.0
Name: bleachfields
Version: 1.0.2
Summary: Tools for bleaching text and JSON of HTML
Home-page: UNKNOWN
Author: Alex Francis
Author-email: afrancis@betterworks.com
License: MIT
Platform: UNKNOWN
Classifier: Intended Audience :: Developers
Classifier: License :: OSI Approved :: MIT License
Classifier: Programming Language :: Python :: 2.7
Requires-Dist: Django (>=1.4.3)
Requires-Dist: jsonfield (>=1.0.3)
Requires-Dist: bleach (>=1.4.1)
